<?xml version="1.0" encoding="UTF-8" ?>
<!DOCTYPE ViewLink SYSTEM "jbo_03_01.dtd">
<!---->
<ViewLink
  xmlns="http://xmlns.oracle.com/bc4j"
  Name="SysC009722860Link"
  Version="12.2.1.11.57"
  InheritPersonalization="merge"
  EntityAssociation="model.assoc.OrderUserAssoc">
  <ViewLinkDefEnd
    Name="UsersVO"
    Cardinality="1"
    Source="true"
    Owner="model.views.UsersVO">
    <DesignTime>
      <Attr Name="_isUpdateable" Value="true"/>
      <Attr Name="_finderName" Value="UsersVO"/>
    </DesignTime>
    <AttrArray Name="Attributes">
      <Item Value="model.views.UsersVO.UserId"/>
    </AttrArray>
  </ViewLinkDefEnd>
  <ViewLinkDefEnd
    Name="OrdersVO"
    Cardinality="-1"
    Owner="model.views.OrdersVO">
    <DesignTime>
      <Attr Name="_isUpdateable" Value="true"/>
      <Attr Name="_finderName" Value="OrdersVO"/>
    </DesignTime>
    <AttrArray Name="Attributes">
      <Item Value="model.views.OrdersVO.CustomerId"/>
    </AttrArray>
  </ViewLinkDefEnd>
</ViewLink>
